src/audio_manager.py
src/audio_tools.py
src/cache.py
src/cli.py
src/config_transfer.py
src/downloader.py
src/exceptions.py
src/hotkey_manager.py
src/interactive_menu.py
src/logging_config.py
src/metadata.py
src/profile_manager.py
src/queue_manager.py
src/search.py
src/soundboard.py
src/sounds_directories.py
src/status_display.py
src/validators.py
muc-0.5.1.dist-info/METADATA
muc-0.5.1.dist-info/WHEEL
muc-0.5.1.dist-info/entry_points.txt
muc-0.5.1.dist-info/licenses/LICENSE
muc-0.5.1.dist-info/RECORD
