Metadata-Version: 2.4
Name: muc
Version: 0.5.1
Summary: Play audio through your microphone in games using hotkeys
Project-URL: Homepage, https://github.com/harshal6927/muc
Project-URL: Website, https://harshallaheri.me/
Author-email: Harshal Laheri <harshal@harshallaheri.me>
License-File: LICENSE
Requires-Python: >=3.13
Requires-Dist: loguru>=0.7.3
Requires-Dist: numpy>=1.24.0
Requires-Dist: pynput>=1.7.6
Requires-Dist: rich-click>=1.9.4
Requires-Dist: sounddevice>=0.4.6
Requires-Dist: soundfile>=0.12.1
Provides-Extra: yt-dlp
Requires-Dist: yt-dlp>=2025.12.8; extra == 'yt-dlp'
